[
  {
    "domains": [
      "akad.de"
    ],
    "alpha_two_code": "DE",
    "web_pages": [
      "http://www.akad.de/"
    ],
    "country": "Germany",
    "state-province": null,
    "name": "AKAD Hochschulen f\u00fcr Berufst\u00e4tige, Fachhochschule Leipzig"
  },
  {
    "domains": [
      "akad.de"
    ],
    "alpha_two_code": "DE",
    "web_pages": [
      "http://www.akad.de/"
    ],
    "country": "Germany",
    "state-province": null,
    "name": "Hochschule f\u00fcr Berufst\u00e4tige Rendsburg"
  },
  {
    "domains": [
      "asfh-berlin.de"
    ],
    "alpha_two_code": "DE",
    "web_pages": [
      "http://www.asfh-berlin.de/"
    ],
    "country": "Germany",
    "state-province": null,
    "name": "Alice-Salomon-Fachhochschule f\u00fcr Sozialarbeit und Sozialp\u00e4dagogik Berlin"
  },
  {
    "domains": [
      "augustana.de"
    ],
    "alpha_two_code": "DE",
    "web_pages": [
      "http://www.augustana.de/"
    ],
    "country": "Germany",
    "state-province": null,
    "name": "Augustana Hochschule Neuendettelsau"
  },
  {
    "domains": [
      "bethel.de"
    ],
    "alpha_two_code": "DE",
    "web_pages": [
      "http://www.bethel.de/kiho/"
    ],
    "country": "Germany",
    "state-province": null,
    "name": "Kirchliche Hochschule Bethel"
  },
  {
    "domains": [
      "bits-iserlohn.de"
    ],
    "alpha_two_code": "DE",
    "web_pages": [
      "http://www.bits-iserlohn.de/"
    ],
    "country": "Germany",
    "state-province": null,
    "name": "BiTS - Business and Information Technology School gGmbH"
  },
  {
    "domains": [
      "cbs.de"
    ],
    "alpha_two_code": "DE",
    "web_pages": [
      "http://www.cbs.de/"
    ],
    "country": "Germany",
    "state-province": null,
    "name": "Cologne Business School"
  },
  {
    "domains": [
      "code.berlin"
    ],
    "alpha_two_code": "DE",
    "web_pages": [
      "http://code.berlin/"
    ],
    "country": "Germany",
    "state-province": null,
    "name": "CODE University of Applied Sciences Berlin"
  },
  {
    "domains": [
      "dhv-speyer.de"
    ],
    "alpha_two_code": "DE",
    "web_pages": [
      "http://www.dhv-speyer.de/"
    ],
    "country": "Germany",
    "state-province": null,
    "name": "Deutsche Hochschule f\u00fcr Verwaltungswissenschaften Speyer"
  },
  {
    "domains": [
      "diploma.de"
    ],
    "alpha_two_code": "DE",
    "web_pages": [
      "http://www.diploma.de/"
    ],
    "country": "Germany",
    "state-province": null,
    "name": "DIPLOMA-Fachhochschule \u00d6lsnitz/Vogtland"
  },
  {
    "domains": [
      "diploma.de"
    ],
    "alpha_two_code": "DE",
    "web_pages": [
      "http://www.diploma.de/"
    ],
    "country": "Germany",
    "state-province": null,
    "name": "Fachhochschule Nordhessen"
  },
  {
    "domains": [
      "dshs-koeln.de"
    ],
    "alpha_two_code": "DE",
    "web_pages": [
      "http://www.dshs-koeln.de/"
    ],
    "country": "Germany",
    "state-province": null,
    "name": "Deutsche Sporthochschule K\u00f6ln"
  },
  {
    "domains": [
      "eap.net"
    ],
    "alpha_two_code": "DE",
    "web_pages": [
      "http://www.eap.net/"
    ],
    "country": "Germany",
    "state-province": null,
    "name": "E.A.P. Europ\u00e4ische Wirtschaftshochschule Berlin"
  },
  {
    "domains": [
      "eba-muenchen.de"
    ],
    "alpha_two_code": "DE",
    "web_pages": [
      "http://www.eba-muenchen.de/"
    ],
    "country": "Germany",
    "state-province": null,
    "name": "Europ\u00e4ische Betriebswirtschafts-Akademie"
  },
  {
    "domains": [
      "ebs.de"
    ],
    "alpha_two_code": "DE",
    "web_pages": [
      "http://www.ebs.de/"
    ],
    "country": "Germany",
    "state-province": null,
    "name": "European Business School Schlo\u00df Reichartshausen"
  },
  {
    "domains": [
      "ecla.de"
    ],
    "alpha_two_code": "DE",
    "web_pages": [
      "http://www.ecla.de/"
    ],
    "country": "Germany",
    "state-province": null,
    "name": "European College of Liberal Arts"
  },
  {
    "domains": [
      "efh-bochum.de"
    ],
    "alpha_two_code": "DE",
    "web_pages": [
      "http://www.efh-bochum.de/"
    ],
    "country": "Germany",
    "state-province": null,
    "name": "Evangelische Fachhochschule Rheinland-Westfalen-Lippe"
  },
  {
    "domains": [
      "eh-darmstadt.de"
    ],
    "alpha_two_code": "DE",
    "web_pages": [
      "https://www.eh-darmstadt.de/"
    ],
    "country": "Germany",
    "state-province": null,
    "name": "Evangelische Fachhochschule Darmstadt"
  },
  {
    "domains": [
      "efh-freiburg.de"
    ],
    "alpha_two_code": "DE",
    "web_pages": [
      "http://www.efh-freiburg.de/"
    ],
    "country": "Germany",
    "state-province": null,
    "name": "Evangelische Fachhochschule Freiburg, Hochschule f\u00fcr Soziale Arbeit, Diakonie und Religionsp\u00e4dagogik"
  },
  {
    "domains": [
      "efh-hannover.de"
    ],
    "alpha_two_code": "DE",
    "web_pages": [
      "http://www.efh-hannover.de/"
    ],
    "country": "Germany",
    "state-province": null,
    "name": "Evangelische Fachhochschule Hannover"
  },
  {
    "domains": [
      "efhlu.de"
    ],
    "alpha_two_code": "DE",
    "web_pages": [
      "http://www.efhlu.de/"
    ],
    "country": "Germany",
    "state-province": null,
    "name": "Evangelische Fachhochschule Ludwigshafen Hochschule f\u00fcr Sozial- und Gesundheitswesen"
  },
  {
    "domains": [
      "efh-reutlingen-ludwigsburg.de"
    ],
    "alpha_two_code": "DE",
    "web_pages": [
      "http://www.efh-reutlingen-ludwigsburg.de/"
    ],
    "country": "Germany",
    "state-province": null,
    "name": "Evangelische Fachhochschule Reutlingen-Ludwigsburg, Hochschule f\u00fcr Soziale Arbeit, Religionsp\u00e4dagogik und Diakonie"
  },
  {
    "domains": [
      "ehs-dresden.de"
    ],
    "alpha_two_code": "DE",
    "web_pages": [
      "http://www.ehs-dresden.de/"
    ],
    "country": "Germany",
    "state-province": null,
    "name": "Evangelische Hochschule f\u00fcr Soziale Arbeit Dresden (FH)"
  },
  {
    "domains": [
      "ems-mainz.de"
    ],
    "alpha_two_code": "DE",
    "web_pages": [
      "http://www.ems-mainz.de/"
    ],
    "country": "Germany",
    "state-province": null,
    "name": "European Management School"
  },
  {
    "domains": [
      "eufh.de"
    ],
    "alpha_two_code": "DE",
    "web_pages": [
      "http://www.eufh.de/"
    ],
    "country": "Germany",
    "state-province": null,
    "name": "Europ\u00e4ische Fachhochschule"
  },
  {
    "domains": [
      "euv-frankfurt-o.de"
    ],
    "alpha_two_code": "DE",
    "web_pages": [
      "http://www.euv-frankfurt-o.de/"
    ],
    "country": "Germany",
    "state-province": null,
    "name": "Europa-Universit\u00e4t Viadrina Frankfurt (Oder)"
  },
  {
    "domains": [
      "evfh-berlin.de"
    ],
    "alpha_two_code": "DE",
    "web_pages": [
      "http://www.evfh-berlin.de/"
    ],
    "country": "Germany",
    "state-province": null,
    "name": "Evangelische Fachhochschule Berlin, Fachhochschule f\u00fcr Sozialarbeit und Sozialp\u00e4dagogik"
  },
  {
    "domains": [
      "evfh-nuernberg.de"
    ],
    "alpha_two_code": "DE",
    "web_pages": [
      "http://www.evfh-nuernberg.de/"
    ],
    "country": "Germany",
    "state-province": null,
    "name": "Evangelische Fachhochschule N\u00fcrnberg"
  },
  {
    "domains": [
      "fern-fh.de"
    ],
    "alpha_two_code": "DE",
    "web_pages": [
      "http://www.fern-fh.de/"
    ],
    "country": "Germany",
    "state-province": null,
    "name": "Fern-Fachhochschule Hamburg"
  },
  {
    "domains": [
      "fernuni-hagen.de"
    ],
    "alpha_two_code": "DE",
    "web_pages": [
      "http://www.fernuni-hagen.de/"
    ],
    "country": "Germany",
    "state-province": null,
    "name": "Fernuniversit\u00e4t Gesamthochschule Hagen"
  },
  {
    "domains": [
      "fh-aachen.de"
    ],
    "alpha_two_code": "DE",
    "web_pages": [
      "http://www.fh-aachen.de/"
    ],
    "country": "Germany",
    "state-province": null,
    "name": "Fachhochschule Aachen"
  },
  {
    "domains": [
      "fh-aschaffenburg.de"
    ],
    "alpha_two_code": "DE",
    "web_pages": [
      "http://www.fh-aschaffenburg.de/"
    ],
    "country": "Germany",
    "state-province": null,
    "name": "Fachhochschule Aschaffenburg"
  },
  {
    "domains": [
      "fh-augsburg.de"
    ],
    "alpha_two_code": "DE",
    "web_pages": [
      "http://www.fh-augsburg.de/"
    ],
    "country": "Germany",
    "state-province": null,
    "name": "Fachhochschule Augsburg"
  },
  {
    "domains": [
      "fh-bad-honnef.de"
    ],
    "alpha_two_code": "DE",
    "web_pages": [
      "http://www.fh-bad-honnef.de/"
    ],
    "country": "Germany",
    "state-province": null,
    "name": "Internationale Fachhochschule Bad Honnef"
  },
  {
    "domains": [
      "fh-biberach.de"
    ],
    "alpha_two_code": "DE",
    "web_pages": [
      "http://www.fh-biberach.de/"
    ],
    "country": "Germany",
    "state-province": null,
    "name": "Fachhochschule Biberach, Hochschule f\u00fcr Bauwesen und Wirtschaft"
  },
  {
    "domains": [
      "fh-bielefeld.de"
    ],
    "alpha_two_code": "DE",
    "web_pages": [
      "http://www.fh-bielefeld.de/"
    ],
    "country": "Germany",
    "state-province": null,
    "name": "Fachhochschule Bielefeld"
  },
  {
    "domains": [
      "fh-bingen.de"
    ],
    "alpha_two_code": "DE",
    "web_pages": [
      "http://www.fh-bingen.de/"
    ],
    "country": "Germany",
    "state-province": null,
    "name": "Fachhochschule Bingen"
  },
  {
    "domains": [
      "fh-bochum.de"
    ],
    "alpha_two_code": "DE",
    "web_pages": [
      "http://www.fh-bochum.de/"
    ],
    "country": "Germany",
    "state-province": null,
    "name": "Fachhochschule Bochum"
  },
  {
    "domains": [
      "hochschule-bonn-rhein-sieg.de",
      "h-brs.de"
    ],
    "alpha_two_code": "DE",
    "web_pages": [
      "http://www.hochschule-bonn-rhein-sieg.de/"
    ],
    "country": "Germany",
    "state-province": null,
    "name": "Hochschule Bonn-Rhein-Sieg"
  },
  {
    "domains": [
      "fh-brandenburg.de"
    ],
    "alpha_two_code": "DE",
    "web_pages": [
      "http://www.fh-brandenburg.de/"
    ],
    "country": "Germany",
    "state-province": null,
    "name": "Fachhochschule Brandenburg"
  },
  {
    "domains": [
      "th-brandenburg.de"
    ],
    "alpha_two_code": "DE",
    "web_pages": [
      "http://www.th-brandenburg.de/"
    ],
    "country": "Germany",
    "state-province": null,
    "name": "Technische Hochschule Brandenburg"
  },
  {
    "domains": [
      "th-deg.de"
    ],
    "alpha_two_code": "DE",
    "web_pages": [
      "http://www.th-deg.de/"
    ],
    "country": "Germany",
    "state-province": null,
    "name": "Technische Hochschule Deggendorf"
  },
  {
    "domains": [
      "fh-dortmund.de"
    ],
    "alpha_two_code": "DE",
    "web_pages": [
      "http://www.fh-dortmund.de/"
    ],
    "country": "Germany",
    "state-province": null,
    "name": "Fachhochschule Dortmund"
  },
  {
    "domains": [
      "hs-duesseldorf.de"
    ],
    "alpha_two_code": "DE",
    "web_pages": [
      "http://www.hs-duesseldorf.de/"
    ],
    "country": "Germany",
    "state-province": null,
    "name": "Hochschule D\u00fcsseldorf"
  },
  {
    "domains": [
      "fhdw.bib.de"
    ],
    "alpha_two_code": "DE",
    "web_pages": [
      "http://www.fhdw.bib.de/"
    ],
    "country": "Germany",
    "state-province": null,
    "name": "Fachhochschule f\u00fcr die Wirtschaft"
  },
  {
    "domains": [
      "fhdw.de"
    ],
    "alpha_two_code": "DE",
    "web_pages": [
      "http://www.fhdw.de/"
    ],
    "country": "Germany",
    "state-province": null,
    "name": "Fachhochschule der Wirtschaft"
  },
  {
    "domains": [
      "fh-eberswalde.de"
    ],
    "alpha_two_code": "DE",
    "web_pages": [
      "http://www.fh-eberswalde.de/"
    ],
    "country": "Germany",
    "state-province": null,
    "name": "Fachhochschule Eberswalde"
  },
  {
    "domains": [
      "fh-erfurt.de"
    ],
    "alpha_two_code": "DE",
    "web_pages": [
      "http://www.fh-erfurt.de/"
    ],
    "country": "Germany",
    "state-province": null,
    "name": "Fachhochschule Erfurt"
  },
  {
    "domains": [
      "fh-flensburg.de"
    ],
    "alpha_two_code": "DE",
    "web_pages": [
      "http://www.fh-flensburg.de/"
    ],
    "country": "Germany",
    "state-province": null,
    "name": "Fachhochschule Flensburg"
  },
  {
    "domains": [
      "fh-frankfurt.de"
    ],
    "alpha_two_code": "DE",
    "web_pages": [
      "http://www.fh-frankfurt.de/"
    ],
    "country": "Germany",
    "state-province": null,
    "name": "Fachhochschule Frankfurt am Main"
  },
  {
    "domains": [
      "fh-fresenius.de"
    ],
    "alpha_two_code": "DE",
    "web_pages": [
      "http://www.fh-fresenius.de/"
    ],
    "country": "Germany",
    "state-province": null,
    "name": "Europa Fachhochschule Fresenius"
  },
  {
    "domains": [
      "fh-furtwangen.de"
    ],
    "alpha_two_code": "DE",
    "web_pages": [
      "http://www.fh-furtwangen.de/"
    ],
    "country": "Germany",
    "state-province": null,
    "name": "Fachhochschule Furtwangen, Hochschule f\u00fcr Technik und Wirtschaft"
  },
  {
    "domains": [
      "fh-gelsenkirchen.de"
    ],
    "alpha_two_code": "DE",
    "web_pages": [
      "http://www.fh-gelsenkirchen.de/"
    ],
    "country": "Germany",
    "state-province": null,
    "name": "Fachhochschule Gelsenkirchen"
  },
  {
    "domains": [
      "fh-giessen.de"
    ],
    "alpha_two_code": "DE",
    "web_pages": [
      "http://www.fh-giessen.de/"
    ],
    "country": "Germany",
    "state-province": null,
    "name": "Fachhochschule Gie\u00dfen-Friedberg"
  },
  {
    "domains": [
      "fh-hamburg.de"
    ],
    "alpha_two_code": "DE",
    "web_pages": [
      "http://www.fh-hamburg.de/"
    ],
    "country": "Germany",
    "state-province": null,
    "name": "Fachhochschule Hamburg"
  },
  {
    "domains": [
      "fh-hannover.de"
    ],
    "alpha_two_code": "DE",
    "web_pages": [
      "http://www.fh-hannover.de/"
    ],
    "country": "Germany",
    "state-province": null,
    "name": "Fachhochschule Hannover"
  },
  {
    "domains": [
      "fh-heidelberg.de"
    ],
    "alpha_two_code": "DE",
    "web_pages": [
      "http://www.fh-heidelberg.de/"
    ],
    "country": "Germany",
    "state-province": null,
    "name": "Fachhochschule Heidelberg"
  },
  {
    "domains": [
      "fh-heilbronn.de"
    ],
    "alpha_two_code": "DE",
    "web_pages": [
      "http://www.fh-heilbronn.de/"
    ],
    "country": "Germany",
    "state-province": null,
    "name": "Fachhochschule Heilbronn, Hochschule f\u00fcr Technik und Wirtschaft"
  },
  {
    "domains": [
      "fh-hildesheim.de"
    ],
    "alpha_two_code": "DE",
    "web_pages": [
      "http://www.fh-hildesheim.de/"
    ],
    "country": "Germany",
    "state-province": null,
    "name": "Fachhochschule Hildesheim/Holzminden/G\u00f6ttingen, Hochschule f\u00fcr angewandte Wissenschaft und Kunst"
  },
  {
    "domains": [
      "fh-hof.de"
    ],
    "alpha_two_code": "DE",
    "web_pages": [
      "http://www.fh-hof.de/"
    ],
    "country": "Germany",
    "state-province": null,
    "name": "Fachhochschule Hof"
  },
  {
    "domains": [
      "thi.de"
    ],
    "alpha_two_code": "DE",
    "web_pages": [
      "https://www.thi.de/"
    ],
    "country": "Germany",
    "state-province": null,
    "name": "Technische Hochschule Ingolstadt"
  },
  {
    "domains": [
      "fh-isny.de"
    ],
    "alpha_two_code": "DE",
    "web_pages": [
      "http://www.fh-isny.de/"
    ],
    "country": "Germany",
    "state-province": null,
    "name": "Fachhochschule und Berufskollegs NTA, Prof.Dr. Gr\u00fcbler gemein. GmbH"
  },
  {
    "domains": [
      "fh-jena.de"
    ],
    "alpha_two_code": "DE",
    "web_pages": [
      "http://www.fh-jena.de/"
    ],
    "country": "Germany",
    "state-province": null,
    "name": "Fachhochschule Jena"
  },
  {
    "domains": [
      "fh-karlsruhe.de"
    ],
    "alpha_two_code": "DE",
    "web_pages": [
      "http://www.fh-karlsruhe.de/"
    ],
    "country": "Germany",
    "state-province": null,
    "name": "Fachhochschule Karlsruhe, Hochschule f\u00fcr Technik"
  },
  {
    "domains": [
      "fh-kempten.de"
    ],
    "alpha_two_code": "DE",
    "web_pages": [
      "http://www.fh-Kempten.de/"
    ],
    "country": "Germany",
    "state-province": null,
    "name": "Fachhochschule Kempten, Hochschule f\u00fcr Technik und Wirtschaft"
  },
  {
    "domains": [
      "fh-kiel.de"
    ],
    "alpha_two_code": "DE",
    "web_pages": [
      "http://www.fh-kiel.de/"
    ],
    "country": "Germany",
    "state-province": null,
    "name": "Fachhochschule Kiel"
  },
  {
    "domains": [
      "fh-kl.de"
    ],
    "alpha_two_code": "DE",
    "web_pages": [
      "http://www.fh-kl.de/"
    ],
    "country": "Germany",
    "state-province": null,
    "name": "Fachhochschule Kaiserslautern"
  },
  {
    "domains": [
      "fh-koblenz.de"
    ],
    "alpha_two_code": "DE",
    "web_pages": [
      "http://www.fh-koblenz.de/"
    ],
    "country": "Germany",
    "state-province": null,
    "name": "Fachhochschule Koblenz"
  },
  {
    "domains": [
      "fh-koeln.de"
    ],
    "alpha_two_code": "DE",
    "web_pages": [
      "http://www.fh-koeln.de/"
    ],
    "country": "Germany",
    "state-province": null,
    "name": "Fachhochschule K\u00f6ln"
  },
  {
    "domains": [
      "fh-konstanz.de"
    ],
    "alpha_two_code": "DE",
    "web_pages": [
      "http://www.fh-konstanz.de/"
    ],
    "country": "Germany",
    "state-province": null,
    "name": "Fachhochschule Konstanz, Hochschule f\u00fcr Technik, Wirtschaft und Gestaltung"
  },
  {
    "domains": [
      "fhkt.de"
    ],
    "alpha_two_code": "DE",
    "web_pages": [
      "http://www.fhkt.de/"
    ],
    "country": "Germany",
    "state-province": null,
    "name": "Staatlich anerkannte Fachhochschule f\u00fcr Kunsttherapie"
  },
  {
    "domains": [
      "fh-landshut.de"
    ],
    "alpha_two_code": "DE",
    "web_pages": [
      "http://www.fh-landshut.de/"
    ],
    "country": "Germany",
    "state-province": null,
    "name": "Fachhochschule Landshut, Hochschule f\u00fcr Wirtschaft - Sozialwesen - Technik"
  },
  {
    "domains": [
      "fh-lausitz.de"
    ],
    "alpha_two_code": "DE",
    "web_pages": [
      "http://www.fh-lausitz.de/"
    ],
    "country": "Germany",
    "state-province": null,
    "name": "Fachhochschule Lausitz"
  },
  {
    "domains": [
      "fh-lippe.de"
    ],
    "alpha_two_code": "DE",
    "web_pages": [
      "http://www.fh-lippe.de/"
    ],
    "country": "Germany",
    "state-province": null,
    "name": "Fachhochschule Lippe"
  },
  {
    "domains": [
      "fh-ludwigshafen.de"
    ],
    "alpha_two_code": "DE",
    "web_pages": [
      "http://www.fh-ludwigshafen.de/"
    ],
    "country": "Germany",
    "state-province": null,
    "name": "Fachhochschule Ludwigshafen, Hochschule f\u00fcr Wirtschaft"
  },
  {
    "domains": [
      "fh-luebeck.de"
    ],
    "alpha_two_code": "DE",
    "web_pages": [
      "http://www.fh-luebeck.de/"
    ],
    "country": "Germany",
    "state-province": null,
    "name": "Fachhochschule L\u00fcbeck"
  },
  {
    "domains": [
      "fh-mainz.de"
    ],
    "alpha_two_code": "DE",
    "web_pages": [
      "http://www.fh-mainz.de/"
    ],
    "country": "Germany",
    "state-province": null,
    "name": "Fachhochschule Mainz"
  },
  {
    "domains": [
      "fh-mannheim.de"
    ],
    "alpha_two_code": "DE",
    "web_pages": [
      "http://www.fh-mannheim.de/"
    ],
    "country": "Germany",
    "state-province": null,
    "name": "Fachhochschule Mannheim, Hochschule f\u00fcr Technik und Gestaltung"
  },
  {
    "domains": [
      "fh-merseburg.de"
    ],
    "alpha_two_code": "DE",
    "web_pages": [
      "http://www.fh-merseburg.de/"
    ],
    "country": "Germany",
    "state-province": null,
    "name": "Fachhochschule Merseburg"
  },
  {
    "domains": [
      "fhm-mittelstand.de"
    ],
    "alpha_two_code": "DE",
    "web_pages": [
      "http://www.fhm-mittelstand.de/"
    ],
    "country": "Germany",
    "state-province": null,
    "name": "Fachhochschule des Mittelstandes (FHM)"
  },
  {
    "domains": [
      "fh-muenchen.de"
    ],
    "alpha_two_code": "DE",
    "web_pages": [
      "http://www.fh-muenchen.de/"
    ],
    "country": "Germany",
    "state-province": null,
    "name": "Fachhochschule M\u00fcnchen"
  },
  {
    "domains": [
      "hm.edu"
    ],
    "alpha_two_code": "DE",
    "web_pages": [
      "http://www.hm.edu/"
    ],
    "country": "Germany",
    "state-province": null,
    "name": "Hochschule M\u00fcnchen"
  },
  {
    "domains": [
      "fh-muenster.de"
    ],
    "alpha_two_code": "DE",
    "web_pages": [
      "http://www.fh-muenster.de/"
    ],
    "country": "Germany",
    "state-province": null,
    "name": "Fachhochschule M\u00fcnster"
  },
  {
    "domains": [
      "fh-nb.de"
    ],
    "alpha_two_code": "DE",
    "web_pages": [
      "http://www.fh-nb.de/"
    ],
    "country": "Germany",
    "state-province": null,
    "name": "Fachhochschule Neubrandenburg"
  },
  {
    "domains": [
      "hs-neu-ulm.de"
    ],
    "alpha_two_code": "DE",
    "web_pages": [
      "http://www.hs-neu-ulm.de/"
    ],
    "country": "Germany",
    "state-province": null,
    "name": "Hochschule Neu-Ulm, Hochschule Neu-Ulm University of applied sciences"
  },
  {
    "domains": [
      "fh-niederrhein.de"
    ],
    "alpha_two_code": "DE",
    "web_pages": [
      "http://www.fh-niederrhein.de/"
    ],
    "country": "Germany",
    "state-province": null,
    "name": "Fachhochschule Niederrhein"
  },
  {
    "domains": [
      "fhnon.de"
    ],
    "alpha_two_code": "DE",
    "web_pages": [
      "http://www.fhnon.de/"
    ],
    "country": "Germany",
    "state-province": null,
    "name": "Fachhochschule Nordostniedersachsen"
  },
  {
    "domains": [
      "fh-nordhausen.de"
    ],
    "alpha_two_code": "DE",
    "web_pages": [
      "http://www.fh-nordhausen.de/"
    ],
    "country": "Germany",
    "state-province": null,
    "name": "Fachhochschule Nordhausen"
  },
  {
    "domains": [
      "fh-nuernberg.de"
    ],
    "alpha_two_code": "DE",
    "web_pages": [
      "http://www.fh-nuernberg.de/"
    ],
    "country": "Germany",
    "state-province": null,
    "name": "Georg-Simon-Ohm-Fachhochschule N\u00fcrnberg"
  },
  {
    "domains": [
      "fh-nuertingen.de"
    ],
    "alpha_two_code": "DE",
    "web_pages": [
      "http://www.fh-nuertingen.de/"
    ],
    "country": "Germany",
    "state-province": null,
    "name": "Fachhochschule N\u00fcrtingen, Hochschule f\u00fcr Wirtschaft, Landwirtschaft und Landespflege"
  },
  {
    "domains": [
      "fhoebb.de"
    ],
    "alpha_two_code": "DE",
    "web_pages": [
      "http://www.fhoebb.de/"
    ],
    "country": "Germany",
    "state-province": null,
    "name": "Fachhochschule f\u00fcr das \u00f6ffentliche Bibliothekswesen Bonn"
  },
  {
    "domains": [
      "fh-offenburg.de"
    ],
    "alpha_two_code": "DE",
    "web_pages": [
      "http://www.fh-offenburg.de/"
    ],
    "country": "Germany",
    "state-province": null,
    "name": "Fachhochschule Offenburg, Hochschule f\u00fcr Technik und Wirtschaft"
  },
  {
    "domains": [
      "fh-oow.de"
    ],
    "alpha_two_code": "DE",
    "web_pages": [
      "http://www.fh-oow.de/"
    ],
    "country": "Germany",
    "state-province": null,
    "name": "Fachhochschule Oldenburg/Ostfriesland/Wilhelmshaven"
  },
  {
    "domains": [
      "fh-osnabrueck.de"
    ],
    "alpha_two_code": "DE",
    "web_pages": [
      "http://www.fh-osnabrueck.de/"
    ],
    "country": "Germany",
    "state-province": null,
    "name": "Fachhochschule Osnabr\u00fcck"
  },
  {
    "domains": [
      "fh-ottersberg.de"
    ],
    "alpha_two_code": "DE",
    "web_pages": [
      "http://www.fh-ottersberg.de/"
    ],
    "country": "Germany",
    "state-province": null,
    "name": "Freie Kunst-Studienst\u00e4tte Ottersberg"
  },
  {
    "domains": [
      "fh-pforzheim.de"
    ],
    "alpha_two_code": "DE",
    "web_pages": [
      "http://www.fh-pforzheim.de/"
    ],
    "country": "Germany",
    "state-province": null,
    "name": "Fachhochschule Pforzheim, Hochschule f\u00fcr Gestaltung, Technik und Wirtschaft"
  },
  {
    "domains": [
      "fh-potsdam.de"
    ],
    "alpha_two_code": "DE",
    "web_pages": [
      "http://www.fh-potsdam.de/"
    ],
    "country": "Germany",
    "state-province": null,
    "name": "Fachhochschule Potsdam"
  },
  {
    "domains": [
      "fh-regensburg.de"
    ],
    "alpha_two_code": "DE",
    "web_pages": [
      "http://www.fh-regensburg.de/"
    ],
    "country": "Germany",
    "state-province": null,
    "name": "Fachhochschule Regensburg"
  },
  {
    "domains": [
      "fh-reutlingen.de"
    ],
    "alpha_two_code": "DE",
    "web_pages": [
      "http://www.fh-reutlingen.de/"
    ],
    "country": "Germany",
    "state-province": null,
    "name": "Fachhochschule Reutlingen, Hochschule f\u00fcr Technik und Wirtschaft"
  },
  {
    "domains": [
      "fh-riedlingen.de"
    ],
    "alpha_two_code": "DE",
    "web_pages": [
      "http://www.fh-riedlingen.de/"
    ],
    "country": "Germany",
    "state-province": null,
    "name": "Deutsch-Ordens Fachhochschule Riedlingen, Hochschule f\u00fcr Wirtschaft"
  },
  {
    "domains": [
      "fh-rosenheim.de"
    ],
    "alpha_two_code": "DE",
    "web_pages": [
      "http://www.fh-rosenheim.de/"
    ],
    "country": "Germany",
    "state-province": null,
    "name": "Fachhochschule Rosenheim, Hochschule f\u00fcr Technik und Wirtschaft"
  },
  {
    "domains": [
      "fh-rottenburg.de"
    ],
    "alpha_two_code": "DE",
    "web_pages": [
      "http://www.fh-rottenburg.de/"
    ],
    "country": "Germany",
    "state-province": null,
    "name": "Fachhochschule Rottenburg, Hochschule f\u00fcr Forstwirtschaft"
  },
  {
    "domains": [
      "fh-schmalkalden.de"
    ],
    "alpha_two_code": "DE",
    "web_pages": [
      "http://www.fh-schmalkalden.de/"
    ],
    "country": "Germany",
    "state-province": null,
    "name": "Fachhochschule Schmalkalden"
  },
  {
    "domains": [
      "fh-schwaebischhall.de"
    ],
    "alpha_two_code": "DE",
    "web_pages": [
      "http://www.fh-schwaebischhall.de/"
    ],
    "country": "Germany",
    "state-province": null,
    "name": "Fachhochschule Schw\u00e4bisch Hall, Hochschule f\u00fcr Gestaltung"
  },
  {
    "domains": [
      "fhs-mannheim.de"
    ],
    "alpha_two_code": "DE",
    "web_pages": [
      "http://www.fhs-mannheim.de/"
    ],
    "country": "Germany",
    "state-province": null,
    "name": "Fachhochschule Mannheim, Hochschule f\u00fcr Sozialwesen"
  },
  {
    "domains": [
      "fhs-moritzburg.de"
    ],
    "alpha_two_code": "DE",
    "web_pages": [
      "http://www.fhs-moritzburg.de/"
    ],
    "country": "Germany",
    "state-province": null,
    "name": "Evangelische Fachhochschule f\u00fcr Religionsp\u00e4dagogik, und Gemeindediakonie Moritzburg"
  },
  {
    "domains": [
      "fh-stralsund.de"
    ],
    "alpha_two_code": "DE",
    "web_pages": [
      "http://www.fh-stralsund.de/"
    ],
    "country": "Germany",
    "state-province": null,
    "name": "Fachhochschule Stralsund"
  },
  {
    "domains": [
      "fh-telekom-leipzig.de"
    ],
    "alpha_two_code": "DE",
    "web_pages": [
      "http://www.fh-telekom-leipzig.de/"
    ],
    "country": "Germany",
    "state-province": null,
    "name": "Deutsche Telekom Fachhochschule Leipzig"
  },
  {
    "domains": [
      "fh-trier.de"
    ],
    "alpha_two_code": "DE",
    "web_pages": [
      "http://www.fh-trier.de/"
    ],
    "country": "Germany",
    "state-province": null,
    "name": "Fachhochschule Trier, Hochschule f\u00fcr Technik, Wirtschaft und Gestaltung"
  },
  {
    "domains": [
      "fht-stuttgart.de"
    ],
    "alpha_two_code": "DE",
    "web_pages": [
      "http://www.fht-stuttgart.de/"
    ],
    "country": "Germany",
    "state-province": null,
    "name": "Fachhochschule Stuttgart, Hochschule f\u00fcr Technik"
  },
  {
    "domains": [
      "fhtw-berlin.de",
      "htw-berlin.de"
    ],
    "alpha_two_code": "DE",
    "web_pages": [
      "https://www.htw-berlin.de/"
    ],
    "country": "Germany",
    "state-province": null,
    "name": "Hochschule f\u00fcr Technik und Wirtschaft Berlin"
  },
  {
    "domains": [
      "hs-ulm.de"
    ],
    "alpha_two_code": "DE",
    "web_pages": [
      "http://www.hs-ulm.de/"
    ],
    "country": "Germany",
    "state-province": null,
    "name": "Hochschule Ulm, Hochschule f\u00fcr Angewandte Wissenschaft"
  },
  {
    "domains": [
      "fhvr.berlin.de"
    ],
    "alpha_two_code": "DE",
    "web_pages": [
      "http://www.fhvr.berlin.de/"
    ],
    "country": "Germany",
    "state-province": null,
    "name": "Fachhochschule f\u00fcr Verwaltung und Rechtspflege Berlin"
  },
  {
    "domains": [
      "fhw-berlin.de"
    ],
    "alpha_two_code": "DE",
    "web_pages": [
      "http://www.fhw-berlin.de/"
    ],
    "country": "Germany",
    "state-province": null,
    "name": "Fachhochschule f\u00fcr Wirtschaft Berlin"
  },
  {
    "domains": [
      "fh-wedel.de"
    ],
    "alpha_two_code": "DE",
    "web_pages": [
      "http://www.fh-wedel.de/"
    ],
    "country": "Germany",
    "state-province": null,
    "name": "Fachhochschule Wedel"
  },
  {
    "domains": [
      "fh-weihenstephan.de"
    ],
    "alpha_two_code": "DE",
    "web_pages": [
      "http://www.fh-weihenstephan.de/"
    ],
    "country": "Germany",
    "state-province": null,
    "name": "Fachhochschule Weihenstephan"
  },
  {
    "domains": [
      "fh-weingarten.de"
    ],
    "alpha_two_code": "DE",
    "web_pages": [
      "http://www.fh-weingarten.de/"
    ],
    "country": "Germany",
    "state-province": null,
    "name": "Fachhochschule Ravensburg-Weingarten"
  },
  {
    "domains": [
      "fh-westkueste.de"
    ],
    "alpha_two_code": "DE",
    "web_pages": [
      "http://www.fh-westkueste.de/"
    ],
    "country": "Germany",
    "state-province": null,
    "name": "Fachhochschule Westk\u00fcste, Hochschule f\u00fcr Wirtschaft und Technik"
  },
  {
    "domains": [
      "fh-wiesbaden.de"
    ],
    "alpha_two_code": "DE",
    "web_pages": [
      "http://www.fh-wiesbaden.de/"
    ],
    "country": "Germany",
    "state-province": null,
    "name": "Fachhochschule Wiesbaden"
  },
  {
    "domains": [
      "fh-wolfenbuettel.de"
    ],
    "alpha_two_code": "DE",
    "web_pages": [
      "http://www.fh-wolfenbuettel.de/"
    ],
    "country": "Germany",
    "state-province": null,
    "name": "Fachhochschule Braunschweig/Wolfenb\u00fcttel"
  },
  {
    "domains": [
      "fh-worms.de"
    ],
    "alpha_two_code": "DE",
    "web_pages": [
      "http://www.fh-worms.de/"
    ],
    "country": "Germany",
    "state-province": null,
    "name": "Fachhochschule Worms"
  },
  {
    "domains": [
      "fhwt.de"
    ],
    "alpha_two_code": "DE",
    "web_pages": [
      "http://www.fhwt.de/"
    ],
    "country": "Germany",
    "state-province": null,
    "name": "Private Fachhochschule f\u00fcr Wirtschaft und Technik Vechta/Diepholz"
  },
  {
    "domains": [
      "fh-wuerzburg.de"
    ],
    "alpha_two_code": "DE",
    "web_pages": [
      "http://www.fh-wuerzburg.de/"
    ],
    "country": "Germany",
    "state-province": null,
    "name": "Fachhochschule W\u00fcrzburg - Schweinfurt"
  },
  {
    "domains": [
      "fh-zwickau.de"
    ],
    "alpha_two_code": "DE",
    "web_pages": [
      "http://www.fh-zwickau.de/"
    ],
    "country": "Germany",
    "state-province": null,
    "name": "Wests\u00e4chsische Hochschule Zwickau (FH)"
  },
  {
    "domains": [
      "fom.de"
    ],
    "alpha_two_code": "DE",
    "web_pages": [
      "http://www.fom.de/"
    ],
    "country": "Germany",
    "state-province": null,
    "name": "Fachhochschule f\u00fcr Oekonomie und Management (FOM)"
  },
  {
    "domains": [
      "fu-berlin.de"
    ],
    "alpha_two_code": "DE",
    "web_pages": [
      "http://www.fu-berlin.de/"
    ],
    "country": "Germany",
    "state-province": null,
    "name": "Freie Universit\u00e4t Berlin"
  },
  {
    "domains": [
      "hanseuni.de"
    ],
    "alpha_two_code": "DE",
    "web_pages": [
      "http://www.hanseuni.de/"
    ],
    "country": "Germany",
    "state-province": null,
    "name": "Private Hanseuniversit\u00e4t"
  },
  {
    "domains": [
      "hcu-hamburg.de"
    ],
    "alpha_two_code": "DE",
    "web_pages": [
      "http://www.hcu-hamburg.de/"
    ],
    "country": "Germany",
    "state-province": null,
    "name": "Hafencity Universit\u00e4t Hamburg"
  },
  {
    "domains": [
      "hdm-stuttgart.de"
    ],
    "alpha_two_code": "DE",
    "web_pages": [
      "http://www.hdm-stuttgart.de/"
    ],
    "country": "Germany",
    "state-province": null,
    "name": "Fachhochschule Stuttgart, Hochschule der Medien"
  },
  {
    "domains": [
      "hertie-school.org"
    ],
    "alpha_two_code": "DE",
    "web_pages": [
      "http://www.hertie-school.org/"
    ],
    "country": "Germany",
    "state-province": null,
    "name": "Hertie School of Governance"
  },
  {
    "domains": [
      "hfb.de"
    ],
    "alpha_two_code": "DE",
    "web_pages": [
      "http://www.hfb.de/"
    ],
    "country": "Germany",
    "state-province": null,
    "name": "Hochschule f\u00fcr Bankwirtschaft (HfB), Private Fachhochschule der Bankakademie"
  },
  {
    "domains": [
      "hfg-gmuend.de"
    ],
    "alpha_two_code": "DE",
    "web_pages": [
      "http://www.hfg-gmuend.de/"
    ],
    "country": "Germany",
    "state-province": null,
    "name": "Fachhochschule Schw\u00e4bisch Gm\u00fcnd, Hochschule f\u00fcr Gestaltung"
  },
  {
    "domains": [
      "hfph.mwn.de"
    ],
    "alpha_two_code": "DE",
    "web_pages": [
      "http://www.hfph.mwn.de/"
    ],
    "country": "Germany",
    "state-province": null,
    "name": "Hochschule f\u00fcr Philosophie M\u00fcnchen"
  },
  {
    "domains": [
      "hfp.mhn.de"
    ],
    "alpha_two_code": "DE",
    "web_pages": [
      "http://www.hfp.mhn.de/"
    ],
    "country": "Germany",
    "state-province": null,
    "name": "Hochschule f\u00fcr Politik (HFP)"
  },
  {
    "domains": [
      "hhl.de"
    ],
    "alpha_two_code": "DE",
    "web_pages": [
      "http://www.hhl.de/"
    ],
    "country": "Germany",
    "state-province": null,
    "name": "Handelshochschule Leipzig"
  },
  {
    "domains": [
      "himh.de"
    ],
    "alpha_two_code": "DE",
    "web_pages": [
      "http://www.himh.de/"
    ],
    "country": "Germany",
    "state-province": null,
    "name": "Hochschule f\u00fcr Internationales Management"
  },
  {
    "domains": [
      "hjs.uni-heidelberg.de"
    ],
    "alpha_two_code": "DE",
    "web_pages": [
      "http://www.hjs.uni-heidelberg.de/"
    ],
    "country": "Germany",
    "state-province": null,
    "name": "Hochschule f\u00fcr J\u00fcdische Studien Heidelberg"
  },
  {
    "domains": [
      "hs-albsig.de"
    ],
    "alpha_two_code": "DE",
    "web_pages": [
      "http://www.hs-albsig.de/"
    ],
    "country": "Germany",
    "state-province": null,
    "name": "Hochschule Albstadt-Sigmaringen"
  },
  {
    "domains": [
      "hs-anhalt.de",
      "student.hs-anhalt.de"
    ],
    "alpha_two_code": "DE",
    "web_pages": [
      "http://www.hs-anhalt.de/"
    ],
    "country": "Germany",
    "state-province": null,
    "name": "Hochschule Anhalt (FH), Hochschule f\u00fcr angewandte Wissenschaften"
  },
  {
    "domains": [
      "hs-bremen.de"
    ],
    "alpha_two_code": "DE",
    "web_pages": [
      "http://www.hs-bremen.de/"
    ],
    "country": "Germany",
    "state-province": null,
    "name": "Hochschule Bremen"
  },
  {
    "domains": [
      "hs-bremerhaven.de"
    ],
    "alpha_two_code": "DE",
    "web_pages": [
      "http://www.hs-bremerhaven.de/"
    ],
    "country": "Germany",
    "state-province": null,
    "name": "Hochschule Bremerhaven"
  },
  {
    "domains": [
      "hs-coburg.de"
    ],
    "alpha_two_code": "DE",
    "web_pages": [
      "http://www.hs-coburg.de/"
    ],
    "country": "Germany",
    "state-province": null,
    "name": "Hochschule Coburg"
  },
  {
    "domains": [
      "h-da.de"
    ],
    "alpha_two_code": "DE",
    "web_pages": [
      "https://www.h-da.de/"
    ],
    "country": "Germany",
    "state-province": null,
    "name": "Hochschule Darmstadt"
  },
  {
    "domains": [
      "hs-esslingen.de"
    ],
    "alpha_two_code": "DE",
    "web_pages": [
      "http://www.hs-esslingen.de/"
    ],
    "country": "Germany",
    "state-province": null,
    "name": "Hochschule Esslingen"
  },
  {
    "domains": [
      "hs-fulda.de"
    ],
    "alpha_two_code": "DE",
    "web_pages": [
      "http://www.hs-fulda.de/"
    ],
    "country": "Germany",
    "state-province": null,
    "name": "Hochschule Fulda"
  },
  {
    "domains": [
      "hs-harz.de"
    ],
    "alpha_two_code": "DE",
    "web_pages": [
      "http://www.hs-harz.de/"
    ],
    "country": "Germany",
    "state-province": null,
    "name": "Hochschule Harz, Hochschule f\u00fcr angewandte Wissenschaften (FH)"
  },
  {
    "domains": [
      "hs-magdeburg.de"
    ],
    "alpha_two_code": "DE",
    "web_pages": [
      "http://www.hs-magdeburg.de/"
    ],
    "country": "Germany",
    "state-province": null,
    "name": "Hochschule Magdeburg-Stendal (FH)"
  },
  {
    "domains": [
      "hs-wismar.de"
    ],
    "alpha_two_code": "DE",
    "web_pages": [
      "http://www.hs-wismar.de/"
    ],
    "country": "Germany",
    "state-province": null,
    "name": "Hochschule Wismar, Fachhochschule f\u00fcr Technik, Wirtschaft und Gestaltung"
  },
  {
    "domains": [
      "hs-zigr.de"
    ],
    "alpha_two_code": "DE",
    "web_pages": [
      "http://www.hs-zigr.de/"
    ],
    "country": "Germany",
    "state-province": null,
    "name": "Hochschule Zittau/G\u00f6rlitz (FH)"
  },
  {
    "domains": [
      "htw-dresden.de"
    ],
    "alpha_two_code": "DE",
    "web_pages": [
      "http://www.htw-dresden.de/"
    ],
    "country": "Germany",
    "state-province": null,
    "name": "Hochschule f\u00fcr Technik und Wirtschaft Dresden (FH)"
  },
  {
    "domains": [
      "htwk-leipzig.de"
    ],
    "alpha_two_code": "DE",
    "web_pages": [
      "http://www.htwk-leipzig.de/"
    ],
    "country": "Germany",
    "state-province": null,
    "name": "Hochschule f\u00fcr Technik, Wirtschaft und Kultur Leipzig (FH)"
  },
  {
    "domains": [
      "htwm.de"
    ],
    "alpha_two_code": "DE",
    "web_pages": [
      "http://www.htwm.de/"
    ],
    "country": "Germany",
    "state-province": null,
    "name": "Hochschule Mittweida (FH)"
  },
  {
    "domains": [
      "htw-saarland.de"
    ],
    "alpha_two_code": "DE",
    "web_pages": [
      "http://www.htw-saarland.de/"
    ],
    "country": "Germany",
    "state-province": null,
    "name": "Hochschule f\u00fcr Technik und Wirtschaft des Saarlandes"
  },
  {
    "domains": [
      "hu-berlin.de"
    ],
    "alpha_two_code": "DE",
    "web_pages": [
      "http://www.hu-berlin.de/"
    ],
    "country": "Germany",
    "state-province": null,
    "name": "Humboldt Universit\u00e4t Berlin"
  },
  {
    "domains": [
      "hwp-hamburg.de"
    ],
    "alpha_two_code": "DE",
    "web_pages": [
      "http://www.hwp-hamburg.de/"
    ],
    "country": "Germany",
    "state-province": null,
    "name": "HWP - Hamburger Universit\u00e4t f\u00fcr Wirtschaft und Politik"
  },
  {
    "domains": [
      "ihi-zittau.de"
    ],
    "alpha_two_code": "DE",
    "web_pages": [
      "http://www.ihi-zittau.de/"
    ],
    "country": "Germany",
    "state-province": null,
    "name": "Internationales Hochschulinstitut Zittau"
  },
  {
    "domains": [
      "international.fh-aalen.de"
    ],
    "alpha_two_code": "DE",
    "web_pages": [
      "http://www.international.fh-aalen.de/"
    ],
    "country": "Germany",
    "state-province": null,
    "name": "Internationale Fachhochschule Aalen"
  },
  {
    "domains": [
      "ism-dortmund.de"
    ],
    "alpha_two_code": "DE",
    "web_pages": [
      "http://www.ism-dortmund.de/"
    ],
    "country": "Germany",
    "state-province": null,
    "name": "International School of Management ISM Dortmund"
  },
  {
    "domains": [
      "isnm.de"
    ],
    "alpha_two_code": "DE",
    "web_pages": [
      "http://www.isnm.de/"
    ],
    "country": "Germany",
    "state-province": null,
    "name": "International School of New Media, University of L\u00fcbeck"
  },
  {
    "domains": [
      "i-u.de"
    ],
    "alpha_two_code": "DE",
    "web_pages": [
      "http://www.i-u.de/"
    ],
    "country": "Germany",
    "state-province": null,
    "name": "International University in Germany"
  },
  {
    "domains": [
      "jacobs-university.de"
    ],
    "alpha_two_code": "DE",
    "web_pages": [
      "http://www.jacobs-university.de/"
    ],
    "country": "Germany",
    "state-province": null,
    "name": "Jacobs University Bremen"
  },
  {
    "domains": [
      "karlshochschule.de"
    ],
    "alpha_two_code": "DE",
    "web_pages": [
      "http://www.karlshochschule.de/"
    ],
    "country": "Germany",
    "state-province": null,
    "name": "Karlshochschule International University"
  },
  {
    "domains": [
      "kath-fh-nord.de"
    ],
    "alpha_two_code": "DE",
    "web_pages": [
      "http://www.kath-fh-nord.de/"
    ],
    "country": "Germany",
    "state-province": null,
    "name": "Katholische Fachhochschule Norddeutschland"
  },
  {
    "domains": [
      "kfb-berlin.de"
    ],
    "alpha_two_code": "DE",
    "web_pages": [
      "http://www.kfb-berlin.de/"
    ],
    "country": "Germany",
    "state-province": null,
    "name": "Katholische Fachhochschule Berlin (KFB)"
  },
  {
    "domains": [
      "kfh-freiburg.de"
    ],
    "alpha_two_code": "DE",
    "web_pages": [
      "http://www.kfh-Freiburg.de/"
    ],
    "country": "Germany",
    "state-province": null,
    "name": "Katholische Fachhochschule Freiburg, Hochschule f\u00fcr Sozialwesen, Religionsp\u00e4dagogik und Pflege"
  },
  {
    "domains": [
      "kfh-mainz.de"
    ],
    "alpha_two_code": "DE",
    "web_pages": [
      "http://www.kfh-mainz.de/"
    ],
    "country": "Germany",
    "state-province": null,
    "name": "Katholische Fachhochschule Mainz"
  },
  {
    "domains": [
      "kfhnw.de"
    ],
    "alpha_two_code": "DE",
    "web_pages": [
      "http://www.kfhnw.de/"
    ],
    "country": "Germany",
    "state-province": null,
    "name": "Katholische Fachhochschule Nordrhein-Westfalen"
  },
  {
    "domains": [
      "kh-berlin.de"
    ],
    "alpha_two_code": "DE",
    "web_pages": [
      "http://www.kh-berlin.de/"
    ],
    "country": "Germany",
    "state-province": null,
    "name": "Kunsthochschule Berlin-Weissensee, Hochschule f\u00fcr Gestaltung"
  },
  {
    "domains": [
      "khsa.de"
    ],
    "alpha_two_code": "DE",
    "web_pages": [
      "http://www.khsa.de/"
    ],
    "country": "Germany",
    "state-province": null,
    "name": "Katholische Hochschule f\u00fcr Soziale Arbeit Saarbr\u00fccken"
  },
  {
    "domains": [
      "ksfh.de"
    ],
    "alpha_two_code": "DE",
    "web_pages": [
      "http://www.ksfh.de/"
    ],
    "country": "Germany",
    "state-province": null,
    "name": "Katholische Stiftungsfachhochschule M\u00fcnchen"
  },
  {
    "domains": [
      "ku-eichstaett.de"
    ],
    "alpha_two_code": "DE",
    "web_pages": [
      "http://www.ku-eichstaett.de/"
    ],
    "country": "Germany",
    "state-province": null,
    "name": "Katholische Universit\u00e4t Eichst\u00e4tt"
  },
  {
    "domains": [
      "kunstakademie-duesseldorf.de"
    ],
    "alpha_two_code": "DE",
    "web_pages": [
      "http://www.kunstakademie-duesseldorf.de/"
    ],
    "country": "Germany",
    "state-province": null,
    "name": "Kunstakademie D\u00fcsseldorf."
  },
  {
    "domains": [
      "merkur-fh.org"
    ],
    "alpha_two_code": "DE",
    "web_pages": [
      "http://www.merkur-fh.org/"
    ],
    "country": "Germany",
    "state-province": null,
    "name": "Merkur Internationale FH Karlsruhe"
  },
  {
    "domains": [
      "merz-akademie.de"
    ],
    "alpha_two_code": "DE",
    "web_pages": [
      "http://www.merz-akademie.de/"
    ],
    "country": "Germany",
    "state-province": null,
    "name": "Merz Akademie, Hochschule f\u00fcr Gestaltung Stuttgart"
  },
  {
    "domains": [
      "mfh-iserlohn.de"
    ],
    "alpha_two_code": "DE",
    "web_pages": [
      "http://www.mfh-iserlohn.de/"
    ],
    "country": "Germany",
    "state-province": null,
    "name": "M\u00e4rkische Fachhochschule Iserlohn"
  },
  {
    "domains": [
      "mh-hannover.de"
    ],
    "alpha_two_code": "DE",
    "web_pages": [
      "http://www.mh-hannover.de/"
    ],
    "country": "Germany",
    "state-province": null,
    "name": "Medizinische Hochschule Hannover"
  },
  {
    "domains": [
      "mh-trossingen.de"
    ],
    "alpha_two_code": "DE",
    "web_pages": [
      "http://www.mh-trossingen.de/"
    ],
    "country": "Germany",
    "state-province": null,
    "name": "Staatliche Hochschule f\u00fcr Musik"
  },
  {
    "domains": [
      "mu-luebeck.de"
    ],
    "alpha_two_code": "DE",
    "web_pages": [
      "http://www.mu-luebeck.de/"
    ],
    "country": "Germany",
    "state-province": null,
    "name": "Medizinische Universit\u00e4t L\u00fcbeck"
  },
  {
    "domains": [
      "muthesius.de"
    ],
    "alpha_two_code": "DE",
    "web_pages": [
      "http://www.muthesius.de/"
    ],
    "country": "Germany",
    "state-province": null,
    "name": "Muthesius-Hochschule, Fachhochschule f\u00fcr Kunst und Gestaltung"
  },
  {
    "domains": [
      "nordakademie.de"
    ],
    "alpha_two_code": "DE",
    "web_pages": [
      "http://www.nordakademie.de/"
    ],
    "country": "Germany",
    "state-province": null,
    "name": "Nordakademie, Staatlich anerkannte private Fachhochschule mit dualen Studieng\u00e4ngen"
  },
  {
    "domains": [
      "paderborn.de"
    ],
    "alpha_two_code": "DE",
    "web_pages": [
      "http://www.paderborn.de/theofak/"
    ],
    "country": "Germany",
    "state-province": null,
    "name": "Theologische Fakult\u00e4t Paderborn"
  },
  {
    "domains": [
      "pfh-goettingen.de"
    ],
    "alpha_two_code": "DE",
    "web_pages": [
      "http://www.pfh-goettingen.de/"
    ],
    "country": "Germany",
    "state-province": null,
    "name": "Private Fachhochschule G\u00f6ttingen"
  },
  {
    "domains": [
      "ph-erfurt.de"
    ],
    "alpha_two_code": "DE",
    "web_pages": [
      "http://www.ph-erfurt.de/"
    ],
    "country": "Germany",
    "state-province": null,
    "name": "P\u00e4dagogische Hochschule Erfurt/M\u00fchlhausen"
  },
  {
    "domains": [
      "ph-freiburg.de"
    ],
    "alpha_two_code": "DE",
    "web_pages": [
      "http://www.ph-freiburg.de/"
    ],
    "country": "Germany",
    "state-province": null,
    "name": "P\u00e4dagogische Hochschule Freiburg"
  },
  {
    "domains": [
      "ph-gmuend.de"
    ],
    "alpha_two_code": "DE",
    "web_pages": [
      "http://www.ph-gmuend.de/"
    ],
    "country": "Germany",
    "state-province": null,
    "name": "P\u00e4dagogische Hochschule Schw\u00e4bisch Gm\u00fcnd"
  },
  {
    "domains": [
      "ph-heidelberg.de"
    ],
    "alpha_two_code": "DE",
    "web_pages": [
      "http://www.ph-heidelberg.de/"
    ],
    "country": "Germany",
    "state-province": null,
    "name": "P\u00e4dagogische Hochschule Heidelberg"
  },
  {
    "domains": [
      "philtheol-augustin.de"
    ],
    "alpha_two_code": "DE",
    "web_pages": [
      "http://www.philtheol-augustin.de/"
    ],
    "country": "Germany",
    "state-province": null,
    "name": "Philosophisch-Theologische Hochschule SVD Sankt Augustin"
  },
  {
    "domains": [
      "ph-karlsruhe.de"
    ],
    "alpha_two_code": "DE",
    "web_pages": [
      "http://www.ph-karlsruhe.de/"
    ],
    "country": "Germany",
    "state-province": null,
    "name": "P\u00e4dagogische Hochschule Karlsruhe"
  },
  {
    "domains": [
      "ph-ludwigsburg.de"
    ],
    "alpha_two_code": "DE",
    "web_pages": [
      "http://www.ph-ludwigsburg.de/"
    ],
    "country": "Germany",
    "state-province": null,
    "name": "P\u00e4dagogische Hochschule Ludwigsburg"
  },
  {
    "domains": [
      "ph-weingarten.de"
    ],
    "alpha_two_code": "DE",
    "web_pages": [
      "http://www.ph-weingarten.de/"
    ],
    "country": "Germany",
    "state-province": null,
    "name": "P\u00e4dagogische Hochschule Weingarten"
  },
  {
    "domains": [
      "popakademie.de"
    ],
    "alpha_two_code": "DE",
    "web_pages": [
      "http://www.popakademie.de/"
    ],
    "country": "Germany",
    "state-province": null,
    "name": "Popakademie Baden-W\u00fcrttemberg"
  },
  {
    "domains": [
      "privatfh-da.de"
    ],
    "alpha_two_code": "DE",
    "web_pages": [
      "http://www.privatfh-da.de/"
    ],
    "country": "Germany",
    "state-province": null,
    "name": "Private FernFachhochschule Darmstadt"
  },
  {
    "domains": [
      "pth-bb.de"
    ],
    "alpha_two_code": "DE",
    "web_pages": [
      "http://www.pth-bb.de/"
    ],
    "country": "Germany",
    "state-province": null,
    "name": "Philosophisch-Theologische Hochschule der Salesianer Don Boscos"
  },
  {
    "domains": [
      "pth-muenster.de"
    ],
    "alpha_two_code": "DE",
    "web_pages": [
      "http://www.pth-muenster.de/"
    ],
    "country": "Germany",
    "state-province": null,
    "name": "Philosophisch-Theologische Hochschule M\u00fcnster"
  },
  {
    "domains": [
      "pthv.de"
    ],
    "alpha_two_code": "DE",
    "web_pages": [
      "http://www.pthv.de/"
    ],
    "country": "Germany",
    "state-province": null,
    "name": "Philosophisch-Theologische Hochschule Vallendar der Gesellschaft des Katholischen Apostolates (Pallottiner)"
  },
  {
    "domains": [
      "rauheshaus.de"
    ],
    "alpha_two_code": "DE",
    "web_pages": [
      "http://www.rauheshaus.de/fachhochschule/"
    ],
    "country": "Germany",
    "state-province": null,
    "name": "Evangelische Fachhochschule f\u00fcr Sozialp\u00e4dagogik der \"Diakonenanstalt des Rauhen Hauses\" Hamburg"
  },
  {
    "domains": [
      "rfh-koeln.de"
    ],
    "alpha_two_code": "DE",
    "web_pages": [
      "http://www.rfh-koeln.de/"
    ],
    "country": "Germany",
    "state-province": null,
    "name": "Rheinische Fachhochschule K\u00f6ln"
  },
  {
    "domains": [
      "ruhr-uni-bochum.de"
    ],
    "alpha_two_code": "DE",
    "web_pages": [
      "http://www.ruhr-uni-bochum.de/"
    ],
    "country": "Germany",
    "state-province": null,
    "name": "Ruhr-Universit\u00e4t Bochum"
  },
  {
    "domains": [
      "rwth-aachen.de"
    ],
    "alpha_two_code": "DE",
    "web_pages": [
      "http://www.rwth-aachen.de/"
    ],
    "country": "Germany",
    "state-province": null,
    "name": "Rheinisch Westf\u00e4lische Technische Hochschule Aachen"
  },
  {
    "domains": [
      "selk.de"
    ],
    "alpha_two_code": "DE",
    "web_pages": [
      "http://www.selk.de/LThH/"
    ],
    "country": "Germany",
    "state-province": null,
    "name": "Lutherische Theologische Hochschule Oberursel"
  },
  {
    "domains": [
      "siewerth-akademie.de"
    ],
    "alpha_two_code": "DE",
    "web_pages": [
      "http://www.siewerth-akademie.de/"
    ],
    "country": "Germany",
    "state-province": null,
    "name": "Gustav-Siewerth-Akademie"
  },
  {
    "domains": [
      "siu-heidelberg.de"
    ],
    "alpha_two_code": "DE",
    "web_pages": [
      "http://www.siu-heidelberg.de/"
    ],
    "country": "Germany",
    "state-province": null,
    "name": "Schiller International University, Heidelberg"
  },
  {
    "domains": [
      "srh-berlin.de"
    ],
    "alpha_two_code": "DE",
    "web_pages": [
      "http://www.srh-berlin.de/"
    ],
    "country": "Germany",
    "state-province": null,
    "name": "SRH University of Applied Sciences"
  },
  {
    "domains": [
      "st-georgen.uni-frankfurt.de"
    ],
    "alpha_two_code": "DE",
    "web_pages": [
      "http://www.st-georgen.uni-frankfurt.de/"
    ],
    "country": "Germany",
    "state-province": null,
    "name": "Philosophisch-Theologische Hochschule Sankt Georgen"
  },
  {
    "domains": [
      "stw.de"
    ],
    "alpha_two_code": "DE",
    "web_pages": [
      "http://www.stw.de/shb/"
    ],
    "country": "Germany",
    "state-province": null,
    "name": "Steinbeis-Hochschule-Berlin"
  },
  {
    "domains": [
      "tfh-berlin.de"
    ],
    "alpha_two_code": "DE",
    "web_pages": [
      "http://www.tfh-berlin.de/"
    ],
    "country": "Germany",
    "state-province": null,
    "name": "Technische Fachhochschule Berlin"
  },
  {
    "domains": [
      "tfh-bochum.de"
    ],
    "alpha_two_code": "DE",
    "web_pages": [
      "http://www.tfh-bochum.de/"
    ],
    "country": "Germany",
    "state-province": null,
    "name": "Technische Fachhochschule Georg Agricola f\u00fcr Rohstoff, Energie und, Umwelt zu Bochum"
  },
  {
    "domains": [
      "tfh-wildau.de"
    ],
    "alpha_two_code": "DE",
    "web_pages": [
      "http://www.tfh-wildau.de/"
    ],
    "country": "Germany",
    "state-province": null,
    "name": "Technische Fachhochschule Wildau"
  },
  {
    "domains": [
      "thh-friedensau.de"
    ],
    "alpha_two_code": "DE",
    "web_pages": [
      "http://www.thh-friedensau.de/"
    ],
    "country": "Germany",
    "state-province": null,
    "name": "Theologische Hochschule Friedensau"
  },
  {
    "domains": [
      "tiho-hannover.de"
    ],
    "alpha_two_code": "DE",
    "web_pages": [
      "http://www.tiho-hannover.de/"
    ],
    "country": "Germany",
    "state-province": null,
    "name": "Tier\u00e4rztliche Hochschule Hannover"
  },
  {
    "domains": [
      "tu-berlin.de"
    ],
    "alpha_two_code": "DE",
    "web_pages": [
      "http://www.tu-berlin.de/"
    ],
    "country": "Germany",
    "state-province": null,
    "name": "Technische Universit\u00e4t Berlin"
  },
  {
    "domains": [
      "tu-bs.de"
    ],
    "alpha_two_code": "DE",
    "web_pages": [
      "http://www.tu-bs.de/"
    ],
    "country": "Germany",
    "state-province": null,
    "name": "Technische Universit\u00e4t Carolo-Wilhelmina Braunschweig"
  },
  {
    "domains": [
      "tu-chemnitz.de"
    ],
    "alpha_two_code": "DE",
    "web_pages": [
      "http://www.tu-chemnitz.de/"
    ],
    "country": "Germany",
    "state-province": null,
    "name": "Technische Universit\u00e4t Chemnitz"
  },
  {
    "domains": [
      "tu-clausthal.de"
    ],
    "alpha_two_code": "DE",
    "web_pages": [
      "http://www.tu-clausthal.de/"
    ],
    "country": "Germany",
    "state-province": null,
    "name": "Technische Universit\u00e4t Clausthal"
  },
  {
    "domains": [
      "tu-cottbus.de"
    ],
    "alpha_two_code": "DE",
    "web_pages": [
      "http://www.tu-cottbus.de/"
    ],
    "country": "Germany",
    "state-province": null,
    "name": "Brandenburgische Technische Universit\u00e4t Cottbus"
  },
  {
    "domains": [
      "tu-darmstadt.de"
    ],
    "alpha_two_code": "DE",
    "web_pages": [
      "https://www.tu-darmstadt.de/"
    ],
    "country": "Germany",
    "state-province": null,
    "name": "Technische Universit\u00e4t Darmstadt"
  },
  {
    "domains": [
      "tu-dresden.de"
    ],
    "alpha_two_code": "DE",
    "web_pages": [
      "http://www.tu-dresden.de/"
    ],
    "country": "Germany",
    "state-province": null,
    "name": "Technische Universit\u00e4t Dresden"
  },
  {
    "domains": [
      "tu-freiberg.de"
    ],
    "alpha_two_code": "DE",
    "web_pages": [
      "http://www.tu-freiberg.de/"
    ],
    "country": "Germany",
    "state-province": null,
    "name": "Technische Universit\u00e4t Bergakademie Freiberg"
  },
  {
    "domains": [
      "tuhh.de"
    ],
    "alpha_two_code": "DE",
    "web_pages": [
      "http://www.tuhh.de/"
    ],
    "country": "Germany",
    "state-province": null,
    "name": "Technische Universit\u00e4t Hamburg"
  },
  {
    "domains": [
      "tu-ilmenau.de"
    ],
    "alpha_two_code": "DE",
    "web_pages": [
      "http://www.tu-ilmenau.de/"
    ],
    "country": "Germany",
    "state-province": null,
    "name": "Technische Universit\u00e4t Ilmenau"
  },
  {
    "domains": [
      "tum.de",
      "tum.edu",
      "mytum.de"
    ],
    "alpha_two_code": "DE",
    "web_pages": [
      "http://www.tum.de/"
    ],
    "country": "Germany",
    "state-province": null,
    "name": "Technische Universit\u00e4t M\u00fcnchen"
  },
  {
    "domains": [
      "uni-augsburg.de"
    ],
    "alpha_two_code": "DE",
    "web_pages": [
      "http://www.uni-augsburg.de/"
    ],
    "country": "Germany",
    "state-province": null,
    "name": "Universit\u00e4t Augsburg"
  },
  {
    "domains": [
      "uni-bamberg.de"
    ],
    "alpha_two_code": "DE",
    "web_pages": [
      "http://www.uni-bamberg.de/"
    ],
    "country": "Germany",
    "state-province": null,
    "name": "Otto-Friedrich Universit\u00e4t Bamberg"
  },
  {
    "domains": [
      "uni-bayreuth.de"
    ],
    "alpha_two_code": "DE",
    "web_pages": [
      "http://www.uni-bayreuth.de/"
    ],
    "country": "Germany",
    "state-province": null,
    "name": "Universit\u00e4t Bayreuth"
  },
  {
    "domains": [
      "uni-bielefeld.de"
    ],
    "alpha_two_code": "DE",
    "web_pages": [
      "http://www.uni-bielefeld.de/"
    ],
    "country": "Germany",
    "state-province": null,
    "name": "Universit\u00e4t Bielefeld"
  },
  {
    "domains": [
      "uni-bonn.de"
    ],
    "alpha_two_code": "DE",
    "web_pages": [
      "http://www.uni-bonn.de/"
    ],
    "country": "Germany",
    "state-province": null,
    "name": "Rheinische Friedrich-Wilhelms Universit\u00e4t Bonn"
  },
  {
    "domains": [
      "uni-bremen.de"
    ],
    "alpha_two_code": "DE",
    "web_pages": [
      "http://www.uni-bremen.de/"
    ],
    "country": "Germany",
    "state-province": null,
    "name": "Universit\u00e4t Bremen"
  },
  {
    "domains": [
      "unibw-hamburg.de"
    ],
    "alpha_two_code": "DE",
    "web_pages": [
      "http://www.unibw-hamburg.de/"
    ],
    "country": "Germany",
    "state-province": null,
    "name": "Universit\u00e4t der Bundeswehr Hamburg"
  },
  {
    "domains": [
      "unibw-muenchen.de"
    ],
    "alpha_two_code": "DE",
    "web_pages": [
      "http://www.unibw-muenchen.de/"
    ],
    "country": "Germany",
    "state-province": null,
    "name": "Universit\u00e4t der Bundeswehr M\u00fcnchen"
  },
  {
    "domains": [
      "tu-dortmund.de"
    ],
    "alpha_two_code": "DE",
    "web_pages": [
      "http://www.tu-dortmund.de/"
    ],
    "country": "Germany",
    "state-province": null,
    "name": "Technische Universit\u00e4t Dortmund"
  },
  {
    "domains": [
      "uni-duesseldorf.de"
    ],
    "alpha_two_code": "DE",
    "web_pages": [
      "http://www.uni-duesseldorf.de/"
    ],
    "country": "Germany",
    "state-province": null,
    "name": "Heinrich-Heine Universit\u00e4t D\u00fcsseldorf"
  },
  {
    "domains": [
      "uni-duisburg-essen.de"
    ],
    "alpha_two_code": "DE",
    "web_pages": [
      "http://www.uni-duisburg-essen.de/"
    ],
    "country": "Germany",
    "state-province": null,
    "name": "Universit\u00e4t Duisburg-Essen"
  },
  {
    "domains": [
      "uni-erfurt.de"
    ],
    "alpha_two_code": "DE",
    "web_pages": [
      "http://www.uni-erfurt.de/phil-theol/"
    ],
    "country": "Germany",
    "state-province": null,
    "name": "Philosophisch-Theologisches Studium Erfurt, Staatlich anerkannte Wissenschaftliche Hochschule"
  },
  {
    "domains": [
      "uni-erfurt.de"
    ],
    "alpha_two_code": "DE",
    "web_pages": [
      "http://www.uni-erfurt.de/"
    ],
    "country": "Germany",
    "state-province": null,
    "name": "Universit\u00e4t Erfurt"
  },
  {
    "domains": [
      "fau.de",
      "uni-erlangen.de"
    ],
    "alpha_two_code": "DE",
    "web_pages": [
      "https://www.fau.de/"
    ],
    "country": "Germany",
    "state-province": null,
    "name": "Friedrich-Alexander Universit\u00e4t Erlangen-N\u00fcrnberg"
  },
  {
    "domains": [
      "uni-flensburg.de"
    ],
    "alpha_two_code": "DE",
    "web_pages": [
      "http://www.uni-flensburg.de/"
    ],
    "country": "Germany",
    "state-province": null,
    "name": "Universit\u00e4t Flensburg"
  },
  {
    "domains": [
      "uni-frankfurt.de"
    ],
    "alpha_two_code": "DE",
    "web_pages": [
      "http://www.uni-frankfurt.de/"
    ],
    "country": "Germany",
    "state-province": null,
    "name": "Johann Wolfgang Goethe Universit\u00e4t Frankfurt am Main"
  },
  {
    "domains": [
      "uni-freiburg.de"
    ],
    "alpha_two_code": "DE",
    "web_pages": [
      "http://www.uni-freiburg.de/"
    ],
    "country": "Germany",
    "state-province": null,
    "name": "Albert-Ludwigs-Universit\u00e4t Freiburg"
  },
  {
    "domains": [
      "uni-giessen.de"
    ],
    "alpha_two_code": "DE",
    "web_pages": [
      "http://www.uni-giessen.de/"
    ],
    "country": "Germany",
    "state-province": null,
    "name": "Justus Liebig Universit\u00e4t Gie\u00dfen"
  },
  {
    "domains": [
      "uni-goettingen.de"
    ],
    "alpha_two_code": "DE",
    "web_pages": [
      "http://www.uni-goettingen.de/"
    ],
    "country": "Germany",
    "state-province": null,
    "name": "Georg-August Universit\u00e4t G\u00f6ttingen"
  },
  {
    "domains": [
      "uni-greifswald.de"
    ],
    "alpha_two_code": "DE",
    "web_pages": [
      "http://www.uni-greifswald.de/"
    ],
    "country": "Germany",
    "state-province": null,
    "name": "Ernst-Moritz-Arndt Universit\u00e4t Greifswald"
  },
  {
    "domains": [
      "uni-halle.de"
    ],
    "alpha_two_code": "DE",
    "web_pages": [
      "http://www.uni-halle.de/"
    ],
    "country": "Germany",
    "state-province": null,
    "name": "Martin-Luther Universit\u00e4t Halle-Wittenberg"
  },
  {
    "domains": [
      "uni-hamburg.de"
    ],
    "alpha_two_code": "DE",
    "web_pages": [
      "http://www.uni-hamburg.de/"
    ],
    "country": "Germany",
    "state-province": null,
    "name": "Universit\u00e4t Hamburg"
  },
  {
    "domains": [
      "uni-hannover.de"
    ],
    "alpha_two_code": "DE",
    "web_pages": [
      "http://www.uni-hannover.de/"
    ],
    "country": "Germany",
    "state-province": null,
    "name": "Universit\u00e4t Hannover"
  },
  {
    "domains": [
      "uni-heidelberg.de"
    ],
    "alpha_two_code": "DE",
    "web_pages": [
      "http://www.uni-heidelberg.de/"
    ],
    "country": "Germany",
    "state-province": null,
    "name": "Ruprecht-Karls-Universit\u00e4t Heidelberg"
  },
  {
    "domains": [
      "uni-hildesheim.de"
    ],
    "alpha_two_code": "DE",
    "web_pages": [
      "http://www.uni-hildesheim.de/"
    ],
    "country": "Germany",
    "state-province": null,
    "name": "Universit\u00e4t Hildesheim"
  },
  {
    "domains": [
      "uni-hohenheim.de"
    ],
    "alpha_two_code": "DE",
    "web_pages": [
      "http://www.uni-hohenheim.de/"
    ],
    "country": "Germany",
    "state-province": null,
    "name": "Universit\u00e4t Hohenheim"
  },
  {
    "domains": [
      "uni-jena.de"
    ],
    "alpha_two_code": "DE",
    "web_pages": [
      "http://www.uni-jena.de/"
    ],
    "country": "Germany",
    "state-province": null,
    "name": "Friedrich-Schiller Universit\u00e4t Jena"
  },
  {
    "domains": [
      "kit.edu"
    ],
    "alpha_two_code": "DE",
    "web_pages": [
      "http://www.kit.edu/"
    ],
    "country": "Germany",
    "state-province": null,
    "name": "Karlsruher Institut f\u00fcr Technologie"
  },
  {
    "domains": [
      "uni-kassel.de"
    ],
    "alpha_two_code": "DE",
    "web_pages": [
      "http://www.uni-kassel.de/"
    ],
    "country": "Germany",
    "state-province": null,
    "name": "Universit\u00e4t Kassel"
  },
  {
    "domains": [
      "uni-kiel.de"
    ],
    "alpha_two_code": "DE",
    "web_pages": [
      "http://www.uni-kiel.de/"
    ],
    "country": "Germany",
    "state-province": null,
    "name": "Christian-Albrechts-Universit\u00e4t Kiel"
  },
  {
    "domains": [
      "uni-kl.de"
    ],
    "alpha_two_code": "DE",
    "web_pages": [
      "http://www.uni-kl.de/"
    ],
    "country": "Germany",
    "state-province": null,
    "name": "Universit\u00e4t Kaiserslautern"
  },
  {
    "domains": [
      "uni-koblenz-landau.de"
    ],
    "alpha_two_code": "DE",
    "web_pages": [
      "http://www.uni-koblenz-landau.de/"
    ],
    "country": "Germany",
    "state-province": null,
    "name": "Universit\u00e4t Koblenz-Landau"
  },
  {
    "domains": [
      "uni-koeln.de"
    ],
    "alpha_two_code": "DE",
    "web_pages": [
      "http://www.uni-koeln.de/"
    ],
    "country": "Germany",
    "state-province": null,
    "name": "Universit\u00e4t K\u00f6ln"
  },
  {
    "domains": [
      "uni-konstanz.de"
    ],
    "alpha_two_code": "DE",
    "web_pages": [
      "http://www.uni-konstanz.de/"
    ],
    "country": "Germany",
    "state-province": null,
    "name": "Universit\u00e4t Konstanz"
  },
  {
    "domains": [
      "uni-leipzig.de"
    ],
    "alpha_two_code": "DE",
    "web_pages": [
      "http://www.uni-leipzig.de/"
    ],
    "country": "Germany",
    "state-province": null,
    "name": "Universit\u00e4t Leipzig"
  },
  {
    "domains": [
      "uni-lueneburg.de"
    ],
    "alpha_two_code": "DE",
    "web_pages": [
      "http://www.uni-lueneburg.de/"
    ],
    "country": "Germany",
    "state-province": null,
    "name": "Universit\u00e4t L\u00fcneburg"
  },
  {
    "domains": [
      "uni-magdeburg.de"
    ],
    "alpha_two_code": "DE",
    "web_pages": [
      "http://www.uni-magdeburg.de/"
    ],
    "country": "Germany",
    "state-province": null,
    "name": "Otto-von-Guericke Universit\u00e4t Magdeburg"
  },
  {
    "domains": [
      "uni-mainz.de"
    ],
    "alpha_two_code": "DE",
    "web_pages": [
      "http://www.uni-mainz.de/"
    ],
    "country": "Germany",
    "state-province": null,
    "name": "Johannes-Gutenberg Universit\u00e4t Mainz"
  },
  {
    "domains": [
      "uni-mannheim.de"
    ],
    "alpha_two_code": "DE",
    "web_pages": [
      "http://www.uni-mannheim.de/"
    ],
    "country": "Germany",
    "state-province": null,
    "name": "Universit\u00e4t Mannheim"
  },
  {
    "domains": [
      "uni-marburg.de"
    ],
    "alpha_two_code": "DE",
    "web_pages": [
      "http://www.uni-marburg.de/"
    ],
    "country": "Germany",
    "state-province": null,
    "name": "Phillips-Universit\u00e4t Marburg"
  },
  {
    "domains": [
      "lmu.de",
      "uni-muenchen.de"
    ],
    "alpha_two_code": "DE",
    "web_pages": [
      "http://www.lmu.de/",
      "http://www.uni-muenchen.de/"
    ],
    "country": "Germany",
    "state-province": null,
    "name": "Ludwig-Maximilians-Universit\u00e4t M\u00fcnchen"
  },
  {
    "domains": [
      "uni-muenster.de",
      "wwu.de"
    ],
    "alpha_two_code": "DE",
    "web_pages": [
      "http://www.uni-muenster.de/",
      "http://www.wwu.de/"
    ],
    "country": "Germany",
    "state-province": null,
    "name": "Westf\u00e4lische Wilhelms-Universit\u00e4t M\u00fcnster"
  },
  {
    "domains": [
      "uol.de",
      "uni-oldenburg.de"
    ],
    "alpha_two_code": "DE",
    "web_pages": [
      "https://uol.de",
      "https://www.uni-oldenburg.de/"
    ],
    "country": "Germany",
    "state-province": null,
    "name": "Carl von Ossietzky Universit\u00e4t Oldenburg"
  },
  {
    "domains": [
      "uni-osnabrueck.de"
    ],
    "alpha_two_code": "DE",
    "web_pages": [
      "http://www.uni-osnabrueck.de/"
    ],
    "country": "Germany",
    "state-province": null,
    "name": "Universit\u00e4t Osnabr\u00fcck"
  },
  {
    "domains": [
      "uni-paderborn.de"
    ],
    "alpha_two_code": "DE",
    "web_pages": [
      "http://www.uni-paderborn.de/"
    ],
    "country": "Germany",
    "state-province": null,
    "name": "Universit\u00e4t Paderborn"
  },
  {
    "domains": [
      "uni-passau.de"
    ],
    "alpha_two_code": "DE",
    "web_pages": [
      "http://www.uni-passau.de/"
    ],
    "country": "Germany",
    "state-province": null,
    "name": "Universit\u00e4t Passau"
  },
  {
    "domains": [
      "uni-potsdam.de"
    ],
    "alpha_two_code": "DE",
    "web_pages": [
      "http://www.uni-potsdam.de/"
    ],
    "country": "Germany",
    "state-province": null,
    "name": "Universit\u00e4t Potsdam"
  },
  {
    "domains": [
      "uni-polsdam.de"
    ],
    "alpha_two_code": "DE",
    "web_pages": [
      "http://www.uni-polsdam.de/"
    ],
    "country": "Germany",
    "state-province": null,
    "name": "Universit\u00e4t Polsdam"
  },
  {
    "domains": [
      "uni-regensburg.de"
    ],
    "alpha_two_code": "DE",
    "web_pages": [
      "http://www.uni-regensburg.de/"
    ],
    "country": "Germany",
    "state-province": null,
    "name": "Universit\u00e4t Regensburg"
  },
  {
    "domains": [
      "uni-rostock.de"
    ],
    "alpha_two_code": "DE",
    "web_pages": [
      "http://www.uni-rostock.de/"
    ],
    "country": "Germany",
    "state-province": null,
    "name": "Universit\u00e4t Rostock"
  },
  {
    "domains": [
      "uni-saarland.de"
    ],
    "alpha_two_code": "DE",
    "web_pages": [
      "http://www.uni-saarland.de/"
    ],
    "country": "Germany",
    "state-province": null,
    "name": "Universit\u00e4t des Saarlandes"
  },
  {
    "domains": [
      "uni-siegen.de"
    ],
    "alpha_two_code": "DE",
    "web_pages": [
      "http://www.uni-siegen.de/"
    ],
    "country": "Germany",
    "state-province": null,
    "name": "Universit\u00e4t Siegen"
  },
  {
    "domains": [
      "uni-stuttgart.de"
    ],
    "alpha_two_code": "DE",
    "web_pages": [
      "http://www.uni-stuttgart.de/"
    ],
    "country": "Germany",
    "state-province": null,
    "name": "Universit\u00e4t Stuttgart"
  },
  {
    "domains": [
      "uni-trier.de"
    ],
    "alpha_two_code": "DE",
    "web_pages": [
      "http://www.uni-trier.de/uni/theo/"
    ],
    "country": "Germany",
    "state-province": null,
    "name": "Theologische Fakult\u00e4t Trier"
  },
  {
    "domains": [
      "uni-trier.de"
    ],
    "alpha_two_code": "DE",
    "web_pages": [
      "http://www.uni-trier.de/"
    ],
    "country": "Germany",
    "state-province": null,
    "name": "Universit\u00e4t Trier"
  },
  {
    "domains": [
      "uni-tuebingen.de"
    ],
    "alpha_two_code": "DE",
    "web_pages": [
      "http://www.uni-tuebingen.de/"
    ],
    "country": "Germany",
    "state-province": null,
    "name": "Eberhard-Karls-Universit\u00e4t T\u00fcbingen"
  },
  {
    "domains": [
      "uni-ulm.de"
    ],
    "alpha_two_code": "DE",
    "web_pages": [
      "http://www.uni-ulm.de/"
    ],
    "country": "Germany",
    "state-province": null,
    "name": "Universit\u00e4t Ulm"
  },
  {
    "domains": [
      "uni-vechta.de"
    ],
    "alpha_two_code": "DE",
    "web_pages": [
      "http://www.uni-vechta.de/"
    ],
    "country": "Germany",
    "state-province": null,
    "name": "Hochschule Vechta"
  },
  {
    "domains": [
      "uni-weimar.de"
    ],
    "alpha_two_code": "DE",
    "web_pages": [
      "http://www.uni-weimar.de/"
    ],
    "country": "Germany",
    "state-province": null,
    "name": "Bauhaus Universit\u00e4t Weimar"
  },
  {
    "domains": [
      "uni-wh.de"
    ],
    "alpha_two_code": "DE",
    "web_pages": [
      "http://www.uni-wh.de/"
    ],
    "country": "Germany",
    "state-province": null,
    "name": "Private Universit\u00e4t Witten/Herdecke"
  },
  {
    "domains": [
      "uni-wuerzburg.de"
    ],
    "alpha_two_code": "DE",
    "web_pages": [
      "http://www.uni-wuerzburg.de/"
    ],
    "country": "Germany",
    "state-province": null,
    "name": "Bayerische Julius-Maximilians-Universit\u00e4t W\u00fcrzburg"
  },
  {
    "domains": [
      "uni-wuppertal.de"
    ],
    "alpha_two_code": "DE",
    "web_pages": [
      "http://www.uni-wuppertal.de/"
    ],
    "country": "Germany",
    "state-province": null,
    "name": "Bergische Universit\u00e4t Gesamthochschule Wuppertal"
  },
  {
    "domains": [
      "uni-wuppertal.de"
    ],
    "alpha_two_code": "DE",
    "web_pages": [
      "http://www.uni-wuppertal.de/inst/kiho/"
    ],
    "country": "Germany",
    "state-province": null,
    "name": "Kirchliche Hochschule Wuppertal"
  },
  {
    "domains": [
      "whu-koblenz.de"
    ],
    "alpha_two_code": "DE",
    "web_pages": [
      "http://www.whu-koblenz.de/"
    ],
    "country": "Germany",
    "state-province": null,
    "name": "Wissenschaftliche Hochschule f\u00fcr Unternehmensf\u00fchrung, Otto-Beisheim Hochschule"
  },
  {
    "domains": [
      "dhbw.de"
    ],
    "alpha_two_code": "DE",
    "web_pages": [
      "http://www.dhbw.de/"
    ],
    "country": "Germany",
    "state-province": null,
    "name": "Duale Hochschule Baden-W\u00fcrttemberg"
  },
  {
    "domains": [
      "heidenheim.dhbw.de"
    ],
    "alpha_two_code": "DE",
    "web_pages": [
      "http://www.heidenheim.dhbw.de/"
    ],
    "country": "Germany",
    "state-province": "null",
    "name": "Duale Hochschule Baden-W\u00fcrttemberg Heidenheim"
  },
  {
    "domains": [
      "cas.dhbw.de"
    ],
    "alpha_two_code": "DE",
    "web_pages": [
      "http://www.cas.dhbw.de/"
    ],
    "country": "Germany",
    "state-province": "null",
    "name": "Duale Hochschule Baden-W\u00fcrttemberg Center for Advanced Studies (CAS)"
  },
  {
    "domains": [
      "dhbw-loerrach.de"
    ],
    "alpha_two_code": "DE",
    "web_pages": [
      "http://www.dhbw-loerrach.de/"
    ],
    "country": "Germany",
    "state-province": "null",
    "name": "Duale Hochschule Baden-W\u00fcrttemberg L\u00f6rrach"
  },
  {
    "domains": [
      "dhbw-mosbach.de",
      "mosbach.dhbw.de"
    ],
    "alpha_two_code": "DE",
    "web_pages": [
      "http://www.dhbw-mosbach.de/",
      "https://www.mosbach.dhbw.de/"
    ],
    "country": "Germany",
    "state-province": "null",
    "name": "Duale Hochschule Baden-W\u00fcrttemberg Mosbach"
  },
  {
    "domains": [
      "ravensburg.dhbw.de"
    ],
    "alpha_two_code": "DE",
    "web_pages": [
      "http://www.ravensburg.dhbw.de/"
    ],
    "country": "Germany",
    "state-province": "null",
    "name": "Duale Hochschule Baden-W\u00fcrttemberg Ravensburg"
  },
  {
    "domains": [
      "dhbw-stuttgart.de"
    ],
    "alpha_two_code": "DE",
    "web_pages": [
      "http://www.dhbw-stuttgart.de/"
    ],
    "country": "Germany",
    "state-province": "null",
    "name": "Duale Hochschule Baden-W\u00fcrttemberg Stuttgart"
  },
  {
    "domains": [
      "dhbw-vs.de"
    ],
    "alpha_two_code": "DE",
    "web_pages": [
      "http://www.dhbw-vs.de/"
    ],
    "country": "Germany",
    "state-province": "null",
    "name": "Duale Hochschule Baden-W\u00fcrttemberg Villingen-Schwenningen"
  },
  {
    "domains": [
      "heilbronn.dhbw.de"
    ],
    "alpha_two_code": "DE",
    "web_pages": [
      "http://www.heilbronn.dhbw.de/"
    ],
    "country": "Germany",
    "state-province": "null",
    "name": "Duale Hochschule Baden-W\u00fcrttemberg Heilbronn"
  },
  {
    "domains": [
      "dhbw-karlsruhe.de",
      "karlsruhe.dhbw.de"
    ],
    "alpha_two_code": "DE",
    "web_pages": [
      "http://www.dhbw-karlsruhe.de/",
      "http://www.karlsruhe.dhbw.de/"
    ],
    "country": "Germany",
    "state-province": "null",
    "name": "Duale Hochschule Baden-W\u00fcrttemberg Karlsruhe"
  },
  {
    "domains": [
      "dhbw-mannheim.de",
      "mannheim.dhbw.de"
    ],
    "alpha_two_code": "DE",
    "web_pages": [
      "http://www.dhbw-mannheim.de/",
      "http://www.mannheim.dhbw.de/"
    ],
    "country": "Germany",
    "state-province": "null",
    "name": "Duale Hochschule Baden-Wuerttemberg Mannheim"
  },
  {
    "domains": [
      "dhbw-mosbach.de",
      "mosbach.dhbw.de"
    ],
    "alpha_two_code": "DE",
    "web_pages": [
      "http://www.dhbw-mosbach.de/",
      "http://www.mosbach.dhbw.de/"
    ],
    "country": "Germany",
    "state-province": "null",
    "name": "Duale Hochschule Baden-W\u00fcrttemberg Mosbach / Bad Mergentheim"
  },
  {
    "domains": [
      "ravensburg.dhbw.de"
    ],
    "alpha_two_code": "DE",
    "web_pages": [
      "http://www.ravensburg.dhbw.de/"
    ],
    "country": "Germany",
    "state-province": "null",
    "name": "Duale Hochschule Baden-W\u00fcrttemberg Ravensburg / Friedrichshafen"
  },
  {
    "domains": [
      "hs-hannover.de",
      "stud.hs-hannover.de"
    ],
    "alpha_two_code": "DE",
    "web_pages": [
      "https://www.hs-hannover.de/"
    ],
    "country": "Germany",
    "state-province": "null",
    "name": "Hochschule Hannover"
  },
  {
    "domains": [
      "ba-bautzen.de"
    ],
    "alpha_two_code": "DE",
    "web_pages": [
      "https://www.ba-bautzen.de/"
    ],
    "country": "Germany",
    "state-province": "null",
    "name": "Staatliche Studienakademie Bautzen"
  },
  {
    "domains": [
      "fom-net.de"
    ],
    "alpha_two_code": "DE",
    "web_pages": [
      "www.fom.de"
    ],
    "country": "Germany",
    "state-province": null,
    "name": "FOM Hochschule f\u00fcr Oekonomie & Management"
  },
  {
    "domains": [
      "thm.de"
    ],
    "alpha_two_code": "DE",
    "web_pages": [
      "www.thm.de"
    ],
    "country": "Germany",
    "state-province": null,
    "name": "Technische Hochschule Mittelhessen"
  },
  {
    "domains": [
      "hwg-lu.de"
    ],
    "alpha_two_code": "DE",
    "web_pages": [
      "www.hwg-lu.de"
    ],
    "country": "Germany",
    "state-province": null,
    "name": "Hochschule f\u00fcr Wirtschaft und Gesellschaft Ludwigshafen"
  },
  {
    "domains": [
      "leuphana.de"
    ],
    "alpha_two_code": "DE",
    "web_pages": [
      "www.leuphana.de"
    ],
    "country": "Germany",
    "state-province": null,
    "name": "Leuphana Universit\u00e4t L\u00fcneburg"
  },
  {
    "domains": [
      "oth-aw.de"
    ],
    "alpha_two_code": "DE",
    "web_pages": [
      "https://www.oth-aw.de/"
    ],
    "country": "Germany",
    "state-province": null,
    "name": "Ostbayerische Technische Hochschule Amberg-Weiden"
  }
]